setup.py
django_user_streams.egg-info/PKG-INFO
django_user_streams.egg-info/SOURCES.txt
django_user_streams.egg-info/dependency_links.txt
django_user_streams.egg-info/top_level.txt
user_streams/__init__.py
user_streams/compat.py
user_streams/models.py
user_streams/tests.py
user_streams/utils.py
user_streams/backends/__init__.py
user_streams/backends/dummy.py
user_streams/backends/user_streams_many_to_many_backend/__init__.py
user_streams/backends/user_streams_many_to_many_backend/models.py
user_streams/backends/user_streams_many_to_many_backend/tests.py
user_streams/backends/user_streams_redis_backend/__init__.py
user_streams/backends/user_streams_redis_backend/models.py
user_streams/backends/user_streams_redis_backend/tests.py
user_streams/backends/user_streams_single_table_backend/__init__.py
user_streams/backends/user_streams_single_table_backend/models.py
user_streams/backends/user_streams_single_table_backend/tests.py