Metadata-Version: 1.0
Name: django-user-streams
Version: 0.6.0
Summary: Simple, fast user news feeds for Django
Home-page: https://github.com/dabapps/django-user-streams
Author: Jamie Matthews
Author-email: UNKNOWN
License: BSD
Platform: UNKNOWN
